odoo/addons/sale_order_disable_user_autosubscribe/README.rst
odoo/addons/sale_order_disable_user_autosubscribe/__init__.py
odoo/addons/sale_order_disable_user_autosubscribe/__manifest__.py
odoo/addons/sale_order_disable_user_autosubscribe/i18n/sale_order_disable_user_autosubscribe.pot
odoo/addons/sale_order_disable_user_autosubscribe/models/__init__.py
odoo/addons/sale_order_disable_user_autosubscribe/models/sale_order.py
odoo/addons/sale_order_disable_user_autosubscribe/readme/CONTRIBUTORS.rst
odoo/addons/sale_order_disable_user_autosubscribe/readme/DESCRIPTION.rst
odoo/addons/sale_order_disable_user_autosubscribe/readme/ROADMAP.rst
odoo/addons/sale_order_disable_user_autosubscribe/static/description/icon.png
odoo/addons/sale_order_disable_user_autosubscribe/static/description/index.html
odoo13_addon_sale_order_disable_user_autosubscribe-13.0.1.0.1.dev3.dist-info/METADATA
odoo13_addon_sale_order_disable_user_autosubscribe-13.0.1.0.1.dev3.dist-info/WHEEL
odoo13_addon_sale_order_disable_user_autosubscribe-13.0.1.0.1.dev3.dist-info/top_level.txt
odoo13_addon_sale_order_disable_user_autosubscribe-13.0.1.0.1.dev3.dist-info/RECORD
